spotoptim/.DS_Store
spotoptim/SpotOptim.html
spotoptim/SpotOptim.py
spotoptim/SpotOptim_files/libs/bootstrap/bootstrap-d6a003b94517c951b2d65075d42fb01b.min.css
spotoptim/SpotOptim_files/libs/bootstrap/bootstrap-icons.css
spotoptim/SpotOptim_files/libs/bootstrap/bootstrap-icons.woff
spotoptim/SpotOptim_files/libs/bootstrap/bootstrap.min.js
spotoptim/SpotOptim_files/libs/clipboard/clipboard.min.js
spotoptim/SpotOptim_files/libs/quarto-html/anchor.min.js
spotoptim/SpotOptim_files/libs/quarto-html/axe/axe-check.js
spotoptim/SpotOptim_files/libs/quarto-html/popper.min.js
spotoptim/SpotOptim_files/libs/quarto-html/quarto-syntax-highlighting-587c61ba64f3a5504c4d52d930310e48.css
spotoptim/SpotOptim_files/libs/quarto-html/quarto.js
spotoptim/SpotOptim_files/libs/quarto-html/tabsets/tabsets.js
spotoptim/SpotOptim_files/libs/quarto-html/tippy.css
spotoptim/SpotOptim_files/libs/quarto-html/tippy.umd.min.js
spotoptim/__init__.py
spotoptim/core/__init__.py
spotoptim/core/data.py
spotoptim/core/experiment.py
spotoptim/data/__init__.py
spotoptim/data/base.py
spotoptim/data/diabetes.py
spotoptim/eda/__init__.py
spotoptim/eda/plots.py
spotoptim/factor_analyzer/__init__.py
spotoptim/factor_analyzer/confirmatory_factor_analyzer.py
spotoptim/factor_analyzer/factor_analyzer.py
spotoptim/factor_analyzer/factor_analyzer_rotator.py
spotoptim/factor_analyzer/factor_analyzer_utils.py
spotoptim/function/.DS_Store
spotoptim/function/__init__.py
spotoptim/function/cd_data.csv
spotoptim/function/forr08a.py
spotoptim/function/mo.py
spotoptim/function/remote.py
spotoptim/function/so.py
spotoptim/function/torch_objective.py
spotoptim/hyperparameters/__init__.py
spotoptim/hyperparameters/parameters.py
spotoptim/hyperparameters/repr_helpers.py
spotoptim/inspection/__init__.py
spotoptim/inspection/importance.py
spotoptim/inspection/predictions.py
spotoptim/mo/__init__.py
spotoptim/mo/mo_mm.py
spotoptim/mo/pareto.py
spotoptim/nn/__init__.py
spotoptim/nn/linear_regressor.py
spotoptim/nn/mlp.py
spotoptim-0.0.160.dist-info/WHEEL
spotoptim-0.0.160.dist-info/METADATA
spotoptim-0.0.160.dist-info/RECORD
