Metadata-Version: 2.3
Name: spotoptim
Version: 0.0.160
Summary: Sequential Parameter Optimization Toolbox
Author: bartzbeielstein
Author-email: bartzbeielstein <32470350+bartzbeielstein@users.noreply.github.com>
Requires-Dist: numpy>=1.24.3
Requires-Dist: scipy>=1.10.1
Requires-Dist: scikit-learn>=1.3.0
Requires-Dist: mkdocs>=1.6.1
Requires-Dist: mkdocs-material>=9.7.0
Requires-Dist: mkdocstrings>=0.30.1
Requires-Dist: mkdocs-gen-files>=0.5.0
Requires-Dist: mkdocs-literate-nav>=0.6.2
Requires-Dist: mkdocs-section-index>=0.3.10
Requires-Dist: mkdocs-exclude>=1.0.2
Requires-Dist: mkdocstrings-python>=1.19.0
Requires-Dist: jupyter>=1.1.1
Requires-Dist: matplotlib>=3.10.7
Requires-Dist: pandas>=2.1.0
Requires-Dist: requests>=2.32.3
Requires-Dist: torch>=2.9.1
Requires-Dist: tensorboard>=2.20.0
Requires-Dist: tabulate>=0.9.0
Requires-Dist: xgboost>=3.1.1
Requires-Dist: seaborn>=0.13.2
Requires-Dist: spotdesirability>=0.0.1
Requires-Dist: jupyter-cache>=1.0.1
Requires-Dist: flake8>=7.3.0
Requires-Dist: dill>=0.4.0
Requires-Dist: statsmodels>=0.14.6
Requires-Python: >=3.13
